pytionary/__init__.py
pytionary/pytionary.py
pytionary/util.py
pytionary-1.dist-info/LICENSE
pytionary-1.dist-info/METADATA
pytionary-1.dist-info/WHEEL
pytionary-1.dist-info/top_level.txt
pytionary-1.dist-info/RECORD
