Metadata-Version: 2.1
Name: pytionary
Version: 1
Summary: Python Dictionary (meaning, synonyms, antonyms, pos)
Home-page: https://github.com/KruzeZab/pytionary
Author: Kruze Zab
Author-email: kruzezab4@gmail.com
License: UNKNOWN
Keywords: dictionary pytionary glossary
Platform: UNKNOWN
Classifier: Programming Language :: Python :: 3
Classifier: License :: OSI Approved :: MIT License
Classifier: Operating System :: OS Independent
Requires-Python: >=3
Requires-Dist: requests
Requires-Dist: beautifulsoup4
